README.rst
setup.cfg
setup.py
weberSchema/CDBConnection.py
weberSchema/CDBCursor.py
weberSchema/CSQLBase.py
weberSchema/CSQLQuery.py
weberSchema/CSQLSchema.py
weberSchema/__init__.py
weberSchema/cursorFuncs.py
weberSchema/exampleCrtTabIDU.py
weberSchema/exampleSchema.py
weberSchema/schemaFuncs.py
weberSchema/testDictParam.py
weberSchema.egg-info/PKG-INFO
weberSchema.egg-info/SOURCES.txt
weberSchema.egg-info/dependency_links.txt
weberSchema.egg-info/not-zip-safe
weberSchema.egg-info/top_level.txt