Metadata-Version: 1.1
Name: weberSchema
Version: 0.0.22
Summary: Public functions library wrote by Weber Juche.
Home-page: https://github.com/Weber-JC/PythonEggs/tree/master/weberSchema
Author: Weber Juche
Author-email: weber.juche@gmail.com
License: MIT
Keywords: weberSchema
Platform: UNKNOWN
Classifier: License :: OSI Approved :: MIT License
Classifier: Programming Language :: Python
Classifier: Intended Audience :: Developers
Classifier: Operating System :: OS Independent
